duo/__init__.py
duo_phone_cleanup/__init__.py
duo_phone_cleanup/__main__.py
duo_phone_cleanup-0.1.0.data/scripts/duo_phone_cleanup
duo_phone_cleanup-0.1.0.dist-info/METADATA
duo_phone_cleanup-0.1.0.dist-info/WHEEL
duo_phone_cleanup-0.1.0.dist-info/top_level.txt
duo_phone_cleanup-0.1.0.dist-info/RECORD
