Metadata-Version: 2.1
Name: duo_phone_cleanup
Version: 0.1.0
Summary: Automatically cleans up phones in the limbo state of "Generic Smartphone" in Duo Security.
Home-page: https://github.com/theias/ias_duo_phone_cleanup
Author: cspeterson,bepstein
Author-email: network@ias.edu
Project-URL: Documentation, https://github.com/theias/ias_duo_phone_cleanup
Project-URL: Bug Tracker, https://github.com/theias/ias_duo_phone_cleanup/issues
Project-URL: Source, https://github.com/theias/ias_duo_phone_cleanup
Classifier: Programming Language :: Python :: 3
Classifier: License :: OSI Approved :: MIT License
Classifier: Operating System :: OS Independent
Requires-Python: >=3.9
Requires-Dist: duo_client<6.0.0,>=5.1.0
